{
    "train_file":"Dataset/Splits/Sentiment/en-AU/Google/train.csv",
    "valid_file":"Dataset/Splits/Sentiment/en-AU/Google/valid.csv",
    "test_file":"Dataset/Splits/Sentiment/en-AU/Google/test.csv",
    "task":"sentiment",
    "model_name_or_path":"google-bert/bert-base-uncased",
    "type":"SEQ_CLS",
    "trust_remote_code":true,
    "torch_dtype":"auto",
    "attn_implementation":"eager",
    "low_cpu_mem_usage":false,
    "lora":false,
    "quant":false,
    "seed":50,
    "num_labels":2,
    "load_best_model_at_end":true,
    "per_device_train_batch_size":8,
    "per_device_eval_batch_size":8,
    "warmup_steps":500,
    "weight_decay":0.01,
    "learning_rate":2e-5,
    "num_train_epochs":30,
    "eval_strategy":"steps",
    "save_steps":400,
    "logging_steps":400,
    "result_dir":"Results/",
    "logging_dir":".logs/",
    "output_dir":".output/",
    "cache_dir":".cache/",
    "token":"[YOUR TOKEN]"
}